jiradata/__init__.py
jiradata/jiradata.py
jiradata-1.2.0.dist-info/entry_points.txt
jiradata-1.2.0.dist-info/WHEEL
jiradata-1.2.0.dist-info/METADATA
jiradata-1.2.0.dist-info/RECORD
