Metadata-Version: 2.1
Name: jiradata
Version: 1.2.0
Summary: Simple JIRA data manipulation
Author: Khalid CK
Author-email: fr.ckhalid@gmail.com
Requires-Python: >=3.7,<4.0
Classifier: Programming Language :: Python :: 3
Classifier: Programming Language :: Python :: 3.7
Classifier: Programming Language :: Python :: 3.8
Requires-Dist: click (>=7.1.2,<8.0.0)
Requires-Dist: ecrivain (>=0.1.2,<0.2.0)
Requires-Dist: pandas (>=1.0.5,<2.0.0)
